LICENSE
MANIFEST.in
README.rst
setup.py
pytss/__about__.py
pytss/__init__.py
pytss/attestationutils.py
pytss/interface.h
pytss/interface.py
pytss/tspi_defines.py
pytss/tspi_exceptions.py
pytss.egg-info/PKG-INFO
pytss.egg-info/SOURCES.txt
pytss.egg-info/dependency_links.txt
pytss.egg-info/not-zip-safe
pytss.egg-info/requires.txt
pytss.egg-info/top_level.txt
pytss/__pycache__/_cffi__xe6c7c5f0x3d3938f1.c