Metadata-Version: 1.0
Name: pytss
Version: 0.1.4
Summary: Python binding to libtspi
Home-page: UNKNOWN
Author: Matthew Garrett
Author-email: matthew.garrett@nebula.com
License: 
